{"_measure": "Armed forces workforce", "_subtopic": "Public sector workforce", "_topic": "Work, pay and benefits", "_version": "1.1", "uri": "work-pay-and-benefits/public-sector-workforce/armed-forces-workforce", "url": "https://www.ethnicity-facts-figures.service.gov.uk/work-pay-and-benefits/public-sector-workforce/armed-forces-workforce/1.1", "data_sources": [{"publisher": "Ministry of Defence", "title": "UK armed forces biannual diversity statistics", "url": "https://www.gov.uk/government/statistics/uk-armed-forces-biannual-diversity-statistics-2017"}], "metadata": {"geographic_coverage": "Other", "frequency": "Twice a year", "time_covered": "2012 to 2017", "data_type": "Administrative", "type_of_statistic": "National statistic", "published_date": "2017-10-11", "next_update_date": "", "qmi_url": "https://www.gov.uk/government/uploads/system/uploads/attachment_data/file/569193/Background_Quality_Report.pdf", "measure": "Armed forces workforce", "subtopic": "Public sector workforce", "topic": "Work, pay and benefits", "version": "1.1"}, "dimensions": [{"_dimension": "Personnel by ethnicity and service, 2017", "metadata": {"measure": "Armed forces workforce", "dimension": "Personnel by ethnicity and service, 2017", "dimension_uri": "armed-forces-workforce/2a1c5c382744772fea01ebaccf28c9f64f4b2414", "guid": "2a1c5c382744772fea01ebaccf28c9f64f4b2414", "measure_guid": "MOD 001", "measure_uri": "armed-forces-workforce", "time_period": "April 2017", "location": "Other", "source_text": "UK armed forces biannual diversity statistics", "source_url": "https://www.gov.uk/government/statistics/uk-armed-forces-biannual-diversity-statistics-2017", "department": "Ministry of Defence", "publication_date": "", "last_update": "June 2017"}, "data": [["Rank", "Service", "Value"], ["Officers", "All Services", "2.4"], ["Officers", "Army", "2.9"], ["Officers", "Royal Air Force", "2.1"], ["Officers", "Royal Navy/Royal Marines", "1.9"], ["Other Ranks", "All Services", "8.3"], ["Other Ranks", "Army", "11.9"], ["Other Ranks", "Royal Air Force", "2.3"], ["Other Ranks", "Royal Navy/Royal Marines", "3.9"]]}, {"_dimension": "Officers by ethnicity and service over time", "metadata": {"measure": "Armed forces workforce", "dimension": "Officers by ethnicity and service over time", "dimension_uri": "armed-forces-workforce/a13c8611aae8dd1e5fee3650c18c9858af915540", "guid": "a13c8611aae8dd1e5fee3650c18c9858af915540", "measure_guid": "MOD 001", "measure_uri": "armed-forces-workforce", "time_period": "2012 to 2017", "location": "Other", "source_text": "UK armed forces biannual diversity statistics", "source_url": "https://www.gov.uk/government/statistics/uk-armed-forces-biannual-diversity-statistics-2017", "department": "Ministry of Defence", "publication_date": "", "last_update": "June 2017"}, "data": [["Year", "Service", "%"], ["Apr-12", "All Services", "2.4"], ["Apr-12", "Army", "2.8"], ["Apr-12", "Royal Air Force", "2.3"], ["Apr-12", "Royal Navy/Royal Marines", "1.8"], ["Apr-13", "All Services", "2.4"], ["Apr-13", "Army", "2.7"], ["Apr-13", "Royal Air Force", "2.3"], ["Apr-13", "Royal Navy/Royal Marines", "1.8"], ["Apr-14", "All Services", "2.4"], ["Apr-14", "Army", "2.7"], ["Apr-14", "Royal Air Force", "2.3"], ["Apr-14", "Royal Navy/Royal Marines", "1.8"], ["Apr-15", "All Services", "2.3"], ["Apr-15", "Army", "2.7"], ["Apr-15", "Royal Air Force", "2.2"], ["Apr-15", "Royal Navy/Royal Marines", "1.8"], ["Apr-16", "All Services", "2.4"], ["Apr-16", "Army", "2.8"], ["Apr-16", "Royal Air Force", "2.2"], ["Apr-16", "Royal Navy/Royal Marines", "1.8"], ["Apr-17", "All Services", "2.4"], ["Apr-17", "Army", "2.9"], ["Apr-17", "Royal Air Force", "2.1"], ["Apr-17", "Royal Navy/Royal Marines", "1.9"]]}, {"_dimension": "Service personnel (all other ranks) over time", "metadata": {"measure": "Armed forces workforce", "dimension": "Service personnel (all other ranks) over time", "dimension_uri": "armed-forces-workforce/93aa1a7d300d64d754589d50de3aa78608533910", "guid": "93aa1a7d300d64d754589d50de3aa78608533910", "measure_guid": "MOD 001", "measure_uri": "armed-forces-workforce", "time_period": "2012 to 2017", "location": "Other", "source_text": "UK armed forces biannual diversity statistics", "source_url": "https://www.gov.uk/government/statistics/uk-armed-forces-biannual-diversity-statistics-2017", "department": "Ministry of Defence", "publication_date": "", "last_update": "June 2017"}, "data": [["Year", "Service", "%"], ["Apr-12", "All Services", "7.9"], ["Apr-12", "Army", "11.1"], ["Apr-12", "Royal Air Force", "1.9"], ["Apr-12", "Royal Navy/Royal Marines", "4.0"], ["Apr-13", "All Services", "8.1"], ["Apr-13", "Army", "11.4"], ["Apr-13", "Royal Air Force", "2.0"], ["Apr-13", "Royal Navy/Royal Marines", "3.9"], ["Apr-14", "All Services", "8.1"], ["Apr-14", "Army", "11.6"], ["Apr-14", "Royal Air Force", "2.0"], ["Apr-14", "Royal Navy/Royal Marines", "3.9"], ["Apr-15", "All Services", "8.0"], ["Apr-15", "Army", "11.5"], ["Apr-15", "Royal Air Force", "2.1"], ["Apr-15", "Royal Navy/Royal Marines", "4.0"], ["Apr-16", "All Services", "8.0"], ["Apr-16", "Army", "11.5"], ["Apr-16", "Royal Air Force", "2.2"], ["Apr-16", "Royal Navy/Royal Marines", "3.9"], ["Apr-17", "All Services", "8.3"], ["Apr-17", "Army", "11.9"], ["Apr-17", "Royal Air Force", "2.3"], ["Apr-17", "Royal Navy/Royal Marines", "3.9"]]}, {"_dimension": "Armed forces personnel by ethnicity and rank", "metadata": {"measure": "Armed forces workforce", "dimension": "Armed forces personnel by ethnicity and rank", "dimension_uri": "armed-forces-workforce/62bcaacc2347d6deac562d0e92bed6db60864422", "guid": "62bcaacc2347d6deac562d0e92bed6db60864422", "measure_guid": "MOD 001", "measure_uri": "armed-forces-workforce", "time_period": "2017", "location": "Other", "source_text": "UK armed forces biannual diversity statistics", "source_url": "https://www.gov.uk/government/statistics/uk-armed-forces-biannual-diversity-statistics-2017", "department": "Ministry of Defence", "publication_date": "", "last_update": "June 2017"}, "data": [["Standard Ethnicity", "NATO code", "%"], ["White", "All Officers", "97.6"], ["White", "OF-1(D)", "97.1"], ["White", "OF-2", "97.6"], ["White", "OF-3", "97.6"], ["White", "OF-4", "97.9"], ["White", "OF-5", "98.2"], ["White", "OF-6 and above", "99.1"], ["White", "All Other Ranks", "91.7"], ["White", "OR-1/OR-2", "92.4"], ["White", "OR-3", "85.6"], ["White", "OR-4", "90.0"], ["White", "OR-6", "92.6"], ["White", "OR-7", "95.1"], ["White", "OR-8", "97.2"], ["White", "OR-9", "98.7"], ["Other", "All Officers", "2.4"], ["Other", "OF-1(D)", "2.9"], ["Other", "OF-2", "2.4"], ["Other", "OF-3", "2.4"], ["Other", "OF-4", "2.1"], ["Other", "OF-5", "1.8"], ["Other", "OF-6 and above", "!"], ["Other", "All Other Ranks", "8.3"], ["Other", "OR-1/OR-2", "7.6"], ["Other", "OR-3", "14.4"], ["Other", "OR-4", "10.0"], ["Other", "OR-6", "7.4"], ["Other", "OR-7", "4.9"], ["Other", "OR-8", "2.8"], ["Other", "OR-9", "1.3"]]}], "downloads": [{"title": "armed_forces_workforce", "file_name": "armed-forces-workforce.csv", "full_path": "https://www.ethnicity-facts-figures.service.gov.uk/work-pay-and-benefits/public-sector-workforce/armed-forces-workforce/1.1/armed-forces-workforce.csv"}]}