{"_measure": "Fuel poverty gap", "uri": "fuel-poverty-gap", "url": "/app/site/20171026_133908.120775_6be7b746-ce94-405f-8d0a-95500204a22e/housing/housing-conditions/fuel-poverty-gap/latest", "data_sources": [{"publisher": "Department for Business, Energy & Industrial Strategy", "title": "Fuel poverty statistics", "url": "https://www.gov.uk/government/collections/fuel-poverty-statistics"}], "metadata": {"geographic_coverage": "England", "frequency": "Annual", "time_covered": "2003 to 2015", "data_type": "Survey", "type_of_statistic": "National Statistics", "published_date": "2017-10-11", "next_update_date": "June 2018", "qmi_url": "", "title": "Fuel poverty gap"}, "dimensions": [{"_dimension": "Average fuel poverty gap by ethnicity over time", "metadata": {"measure": "Fuel poverty gap", "dimension": "Average fuel poverty gap by ethnicity over time", "dimension_uri": "fuel-poverty-gap/265f67c8821ef05b2bbc7bf85b881222770032d8", "guid": "265f67c8821ef05b2bbc7bf85b881222770032d8", "measure_guid": "BEIS 007", "measure_uri": "fuel-poverty-gap", "time_period": "2003 to 2015", "location": "England", "source_text": "Fuel poverty statistics", "source_url": "https://www.gov.uk/government/collections/fuel-poverty-statistics", "department": "Department for Business, Energy & Industrial Strategy", "publication_date": "September 2013", "last_update": "June 2017"}, "data": [["Ethnicity", "Year", "\u00a3"], ["White", "2003", "229"], ["White", "2004", "236"], ["White", "2005", "260"], ["White", "2006", "334"], ["White", "2007", "333"], ["White", "2008", "345"], ["White", "2009", "368"], ["White", "2010", "370"], ["White", "2011", "407"], ["White", "2012", "407"], ["White", "2013", "380"], ["White", "2014", "377"], ["White", "2015", "358"], ["Other", "2003", "219"], ["Other", "2004", "228"], ["Other", "2005", "212"], ["Other", "2006", "271"], ["Other", "2007", "276"], ["Other", "2008", "304"], ["Other", "2009", "304"], ["Other", "2010", "281"], ["Other", "2011", "298"], ["Other", "2012", "324"], ["Other", "2013", "391"], ["Other", "2014", "358"], ["Other", "2015", "331"]]}], "downloads": [{"title": "Average fuel poverty gap", "file_name": "average-fuel-poverty-gap.csv", "full_path": "/app/site/20171026_133908.120775_6be7b746-ce94-405f-8d0a-95500204a22e/housing/housing-conditions/fuel-poverty-gap/latest/average-fuel-poverty-gap.csv"}]}